sanic_thumbnails/__init__.py
sanic_thumbnails/storage_backends.py
sanic_thumbnails/thumbnail.py
sanic_thumbnails/utils.py
Sanic_thumbnails-0.3.0.dist-info/LICENSE
Sanic_thumbnails-0.3.0.dist-info/METADATA
Sanic_thumbnails-0.3.0.dist-info/WHEEL
Sanic_thumbnails-0.3.0.dist-info/top_level.txt
Sanic_thumbnails-0.3.0.dist-info/RECORD
